teqp/__init__.py
teqp/fluiddata/dev/fluids/1-Butene.json
teqp/fluiddata/dev/fluids/Acetone.json
teqp/fluiddata/dev/fluids/Air.json
teqp/fluiddata/dev/fluids/Ammonia.json
teqp/fluiddata/dev/fluids/Argon.json
teqp/fluiddata/dev/fluids/Benzene.json
teqp/fluiddata/dev/fluids/CarbonDioxide.json
teqp/fluiddata/dev/fluids/CarbonMonoxide.json
teqp/fluiddata/dev/fluids/CarbonylSulfide.json
teqp/fluiddata/dev/fluids/cis-2-Butene.json
teqp/fluiddata/dev/fluids/CycloHexane.json
teqp/fluiddata/dev/fluids/Cyclopentane.json
teqp/fluiddata/dev/fluids/CycloPropane.json
teqp/fluiddata/dev/fluids/D4.json
teqp/fluiddata/dev/fluids/D5.json
teqp/fluiddata/dev/fluids/D6.json
teqp/fluiddata/dev/fluids/Deuterium.json
teqp/fluiddata/dev/fluids/Dichloroethane.json
teqp/fluiddata/dev/fluids/DiethylEther.json
teqp/fluiddata/dev/fluids/DimethylCarbonate.json
teqp/fluiddata/dev/fluids/DimethylEther.json
teqp/fluiddata/dev/fluids/Ethane.json
teqp/fluiddata/dev/fluids/Ethanol.json
teqp/fluiddata/dev/fluids/EthylBenzene.json
teqp/fluiddata/dev/fluids/Ethylene.json
teqp/fluiddata/dev/fluids/EthyleneOxide.json
teqp/fluiddata/dev/fluids/Fluorine.json
teqp/fluiddata/dev/fluids/HeavyWater.json
teqp/fluiddata/dev/fluids/Helium.json
teqp/fluiddata/dev/fluids/HFE143m.json
teqp/fluiddata/dev/fluids/Hydrogen.json
teqp/fluiddata/dev/fluids/HydrogenChloride.json
teqp/fluiddata/dev/fluids/HydrogenSulfide.json
teqp/fluiddata/dev/fluids/IsoButane.json
teqp/fluiddata/dev/fluids/IsoButene.json
teqp/fluiddata/dev/fluids/Isohexane.json
teqp/fluiddata/dev/fluids/Isopentane.json
teqp/fluiddata/dev/fluids/Krypton.json
teqp/fluiddata/dev/fluids/m-Xylene.json
teqp/fluiddata/dev/fluids/MD2M.json
teqp/fluiddata/dev/fluids/MD3M.json
teqp/fluiddata/dev/fluids/MD4M.json
teqp/fluiddata/dev/fluids/MDM.json
teqp/fluiddata/dev/fluids/Methane.json
teqp/fluiddata/dev/fluids/Methanol.json
teqp/fluiddata/dev/fluids/MethylLinoleate.json
teqp/fluiddata/dev/fluids/MethylLinolenate.json
teqp/fluiddata/dev/fluids/MethylOleate.json
teqp-0.23.1.dist-info/METADATA
teqp-0.23.1.dist-info/WHEEL
teqp-0.23.1.dist-info/licenses/LICENSE.md
teqp-0.23.1.dist-info/RECORD
