Metadata-Version: 2.1
Name: teqp
Version: 0.23.1
Summary: teqp: Templated EQuation of state Package
Author-Email: Ian Bell <ian.bell@nist.gov>
Project-URL: Homepage, https://github.com/usnistgov/teqp
Requires-Python: >=3.8
